setup.py
ghtools/__init__.py
ghtools/api.py
ghtools/cli.py
ghtools/exceptions.py
ghtools/identifier.py
ghtools/util.py
ghtools.egg-info/PKG-INFO
ghtools.egg-info/SOURCES.txt
ghtools.egg-info/dependency_links.txt
ghtools.egg-info/entry_points.txt
ghtools.egg-info/requires.txt
ghtools.egg-info/top_level.txt
ghtools/command/__init__.py
ghtools/command/browse.py
ghtools/command/list_members.py
ghtools/command/login.py
ghtools/command/migrate_project.py
ghtools/command/migrate_teams.py
ghtools/command/migrate_wiki.py
ghtools/command/migration_status.py
ghtools/command/org.py
ghtools/command/repo.py
ghtools/command/status.py
ghtools/github/__init__.py
ghtools/github/organisation.py
ghtools/github/repo.py
ghtools/migrators/__init__.py
ghtools/migrators/comments.py
ghtools/migrators/hooks.py
ghtools/migrators/issues.py
ghtools/migrators/repo.py
ghtools/migrators/teams.py
ghtools/migrators/wiki.py