Metadata-Version: 1.0
Name: ghtools
Version: 0.23.0
Summary: ghtools: tools for interacting with the GitHub API
Home-page: https://github.com/alphagov/ghtools
Author: Government Digital Service
Author-email: nick@whiteink.com
License: MIT
Keywords: sysadmin git github api
Platform: UNKNOWN
